{
	"schemaVersion": 1,
	"id": "octocomputing",
	"version": "${version}",
	"name": "OctoComputing",
	"description": "Adds more realistic leaf quantity drops from leaf blocks. As well as some \"related\" things.",
	"authors": [
		"KrazyMiner001"
	],
	"contact": {
		"sources": "https://github.com/Radford-House/studious-octo-computing-machine"
	},
	"license": "MIT",
	"icon": "assets/octocomputing/icon.png",
	"environment": "*",
	"entrypoints": {
		"main": [
          "tech.krazyminer001.OctoComputing"
		],
		"client": [
          "tech.krazyminer001.OctoComputingClient"
		],
		"fabric-datagen": [
          "tech.krazyminer001.OctoComputingDataGenerator"
		],
		"emi": [
          "tech.krazyminer001.compat.emi.OctoComputingEmiPlugin"
		]
	},
	"mixins": [
		"octocomputing.mixins.json"
	],
	"depends": {
		"fabricloader": ">=0.15.0",
		"minecraft": "~1.20.6",
		"java": ">=21",
		"fabric-api": "*"
	},
	"suggests": {
		"another-mod": "*"
	}
}